winkeyerserial/JetBrainsMono-Regular.ttf
winkeyerserial/__init__.py
winkeyerserial/__main__.py
winkeyerserial/k6gte-winkeyerserial-128.png
winkeyerserial/k6gte-winkeyerserial-32.png
winkeyerserial/k6gte-winkeyerserial-64.png
winkeyerserial/k6gte-winkeyerserial.desktop
winkeyerserial/main.ui
winkeyerserial/settings.py
winkeyerserial/settings.ui
winkeyerserial-25.9.13.1.dist-info/licenses/LICENSE
winkeyerserial-25.9.13.1.dist-info/METADATA
winkeyerserial-25.9.13.1.dist-info/WHEEL
winkeyerserial-25.9.13.1.dist-info/entry_points.txt
winkeyerserial-25.9.13.1.dist-info/top_level.txt
winkeyerserial-25.9.13.1.dist-info/RECORD
