Metadata-Version: 2.4
Name: winkeyerserial
Version: 25.9.13.1
Summary: Talk to K1EL winkeyer
Author-email: Michael Bridak <michael.bridak@gmail.com>
License: GPL-3.0-or-later
Project-URL: Homepage, https://github.com/mbridak/PyWinKeyerSerial
Project-URL: Bug Tracker, https://github.com/mbridak/PyWinKeyerSerial/issues
Classifier: Programming Language :: Python :: 3
Classifier: Development Status :: 5 - Production/Stable
Classifier: License :: OSI Approved :: GNU General Public License v3 (GPLv3)
Classifier: Environment :: X11 Applications :: Qt
Classifier: Operating System :: POSIX :: Linux
Classifier: Intended Audience :: End Users/Desktop
Classifier: Natural Language :: English
Classifier: Topic :: Communications :: Ham Radio
Requires-Python: >=3.10
License-File: LICENSE
Requires-Dist: PyQt6
Requires-Dist: pySerial
Dynamic: license-file
